COPYRIGHT.txt
LICENSE.txt
MANIFEST.in
README.txt
eggtestinfo-0.2.2-py2.6.egg
setup.py
Products/__init__.py
Products.CMFTopic.egg-info/PKG-INFO
Products.CMFTopic.egg-info/SOURCES.txt
Products.CMFTopic.egg-info/dependency_links.txt
Products.CMFTopic.egg-info/entry_points.txt
Products.CMFTopic.egg-info/namespace_packages.txt
Products.CMFTopic.egg-info/not-zip-safe
Products.CMFTopic.egg-info/requires.txt
Products.CMFTopic.egg-info/test_info.txt
Products.CMFTopic.egg-info/top_level.txt
Products/CMFTopic/AbstractCriterion.py
Products/CMFTopic/CHANGES.txt
Products/CMFTopic/COPYRIGHT.txt
Products/CMFTopic/DateCriteria.py
Products/CMFTopic/ListCriterion.py
Products/CMFTopic/README.txt
Products/CMFTopic/SimpleIntCriterion.py
Products/CMFTopic/SimpleStringCriterion.py
Products/CMFTopic/SortCriterion.py
Products/CMFTopic/Topic.py
Products/CMFTopic/__init__.py
Products/CMFTopic/configure.zcml
Products/CMFTopic/exportimport.py
Products/CMFTopic/permissions.py
Products/CMFTopic/testing.py
Products/CMFTopic/version.txt
Products/CMFTopic/help/Overview.stx
Products/CMFTopic/help/Topics.stx
Products/CMFTopic/interfaces/__init__.py
Products/CMFTopic/profiles/default/skins.xml
Products/CMFTopic/profiles/default/types.xml
Products/CMFTopic/profiles/default/workflows.xml
Products/CMFTopic/profiles/default/types/Topic.xml
Products/CMFTopic/skins/zpt_topic/friendlydatec_editform.pt
Products/CMFTopic/skins/zpt_topic/listc_edit.pt
Products/CMFTopic/skins/zpt_topic/sic_edit.pt
Products/CMFTopic/skins/zpt_topic/sort_edit.pt
Products/CMFTopic/skins/zpt_topic/ssc_edit.pt
Products/CMFTopic/skins/zpt_topic/topic_addCriterion.py
Products/CMFTopic/skins/zpt_topic/topic_criteria_form.pt
Products/CMFTopic/skins/zpt_topic/topic_deleteCriteria.py
Products/CMFTopic/skins/zpt_topic/topic_editCriteria.py
Products/CMFTopic/skins/zpt_topic/topic_edit_control.py
Products/CMFTopic/skins/zpt_topic/topic_edit_form.py
Products/CMFTopic/skins/zpt_topic/topic_edit_template.pt
Products/CMFTopic/skins/zpt_topic/topic_icon.gif
Products/CMFTopic/skins/zpt_topic/topic_view.py
Products/CMFTopic/skins/zpt_topic/topic_view_template.pt
Products/CMFTopic/tests/__init__.py
Products/CMFTopic/tests/common.py
Products/CMFTopic/tests/test_DateC.py
Products/CMFTopic/tests/test_ListC.py
Products/CMFTopic/tests/test_SIC.py
Products/CMFTopic/tests/test_SSC.py
Products/CMFTopic/tests/test_SortC.py
