Metadata-Version: 1.0
Name: Products.CMFTopic
Version: 2.3.0-beta
Summary: Topic product for the Zope Content Management Framework
Home-page: http://pypi.python.org/pypi/Products.CMFTopic
Author: Zope Foundation and Contributors
Author-email: zope-cmf@zope.org
License: ZPL 2.1 (http://www.zope.org/Resources/License/ZPL-2.1)
Keywords: web application server zope zope2 cmf
Platform: UNKNOWN
Classifier: Development Status :: 5 - Production/Stable
Classifier: Framework :: Plone
Classifier: Framework :: Zope2
Classifier: Intended Audience :: Developers
Classifier: License :: OSI Approved :: Zope Public License
Classifier: Programming Language :: Python
Classifier: Topic :: Software Development
Classifier: Topic :: Software Development :: Libraries :: Application Frameworks
